proxmox_backup_removable_datastore/__init__.py
proxmox_backup_removable_datastore/main.py
proxmox_backup_removable_datastore/models/__init__.py
proxmox_backup_removable_datastore/models/datastore.py
proxmox_backup_removable_datastore/models/prunejob.py
proxmox_backup_removable_datastore/models/syncjob.py
proxmox_backup_removable_datastore/models/utils.py
proxmox_backup_removable_datastore-1.0.3.dist-info/LICENCE
proxmox_backup_removable_datastore-1.0.3.dist-info/METADATA
proxmox_backup_removable_datastore-1.0.3.dist-info/WHEEL
proxmox_backup_removable_datastore-1.0.3.dist-info/entry_points.txt
proxmox_backup_removable_datastore-1.0.3.dist-info/top_level.txt
proxmox_backup_removable_datastore-1.0.3.dist-info/RECORD
