Metadata-Version: 2.1
Name: proxmox-backup-removable-datastore
Version: 1.0.3
Summary: Sync proxmox backup datastore to removable datastore
Author-email: Mathieu Fruchet <mathieu.fruchet@greenitsolutions.fr>
Maintainer-email: Green IT Solutions <support@greenitsolutions.fr>
License: GPL-3.0-or-later
Project-URL: Homepage, https://gitlab.greenitsolutions.fr/01-greenitsolutions/proxmox-backup-removable-datastore
Requires-Python: >=3.9
License-File: LICENCE
